mlpro_int_sb3/__init__.py
mlpro_int_sb3/wrappers/__init__.py
mlpro_int_sb3/wrappers/basics.py
mlpro_int_sb3-1.0.7.dist-info/licenses/LICENSE
mlpro_int_sb3-1.0.7.dist-info/METADATA
mlpro_int_sb3-1.0.7.dist-info/WHEEL
mlpro_int_sb3-1.0.7.dist-info/top_level.txt
mlpro_int_sb3-1.0.7.dist-info/RECORD
