Metadata-Version: 2.4
Name: mlpro-int-sb3
Version: 1.0.7
Summary: MLPro: Integration StableBaselines3
Home-page: https://mlpro-int-sb3.readthedocs.io
Author: MLPro Team
Author-email: mlpro@listen.fh-swf.de
Project-URL: Bug Tracker, https://mlpro-int-sb3.readthedocs.io
Classifier: Programming Language :: Python :: 3
Classifier: License :: OSI Approved :: Apache Software License
Classifier: Operating System :: OS Independent
Requires-Python: >=3.11
License-File: LICENSE
Provides-Extra: full
Requires-Dist: mlpro_int_gymnasium[full]>=1.0.4; extra == "full"
Requires-Dist: mlpro_int_mujoco[full]>=1.0.3; extra == "full"
Requires-Dist: mlpro>=2.1.0; extra == "full"
Requires-Dist: stable_baselines3>=2.3.0; extra == "full"
Requires-Dist: sb3-contrib>=2.2.1; extra == "full"
Requires-Dist: torch<=2.3.1,>=2.0.0; extra == "full"
Requires-Dist: numpy<=1.26.4,>=1.0.0; extra == "full"
Requires-Dist: setuptools>=75.0.0; extra == "full"
Dynamic: license-file
